template_res/__init__.py
template_res/main.py
template_res/server.py
template_res/template.py
template_res/res/__init__.py
p_template_res-1.0.0.dist-info/LICENSE
p_template_res-1.0.0.dist-info/METADATA
p_template_res-1.0.0.dist-info/WHEEL
p_template_res-1.0.0.dist-info/entry_points.txt
p_template_res-1.0.0.dist-info/top_level.txt
p_template_res-1.0.0.dist-info/RECORD
