Metadata-Version: 2.1
Name: p-template-res
Version: 1.0.0
Summary: temple tools
Author: pengjun
Author-email: mr_lonely@foxmail.com
Classifier: Programming Language :: Python :: 3
Classifier: License :: OSI Approved :: MIT License
Classifier: Operating System :: OS Independent
Requires-Python: >=3.7
License-File: LICENSE
Requires-Dist: requests
Requires-Dist: mutagen
